[
  {
    "name": "",
    "header": "",
    "footer": "",
    "id": null
  },
  {
    "name": "namecix5-",
    "header": "headerJy8: Y]o. nCFhE:IZ1",
    "footer": "footerzgYY ]J+/7I ",
    "id": null
  },
  {
    "name": "name:(  N6O",
    "header": "header VipB3m9ZlDvho k!",
    "footer": "footerKxr]-Nj",
    "id": null
  },
  {
    "name": "name\\ ",
    "header": "header ]",
    "footer": "footerl'Gx.[6Ud \" ",
    "id": null
  },
  {
    "name": "nameRf m&X~",
    "header": "headerZYXbc (nfu",
    "footer": "footernT\"x\" Dn VF[iCJa\"",
    "id": null
  },
  {
    "name": "name",
    "header": "headerw )y  X7V|X",
    "footer": "footerBI1",
    "id": null
  }
]